SDDB/DatabaseDiscord.py
SDDB/__init__.py
SDDB-0.0.4.dist-info/LICENSE
SDDB-0.0.4.dist-info/METADATA
SDDB-0.0.4.dist-info/WHEEL
SDDB-0.0.4.dist-info/top_level.txt
SDDB-0.0.4.dist-info/RECORD
