Metadata-Version: 2.1
Name: SDDB
Version: 0.0.4
Summary: UNKNOWN
Home-page: https://github.com/Kelzorz/SDDB
Author: Kelzorz
Author-email: 43789359+Kelzorz@users.noreply.github.com
License: /*
Requires-Dist: discord.py (>=1.4.0)
